{
  "slug": "diggersby",
  "name": "Diggersby",
  "dexNumber": 660,
  "implemented": true,
  "types": [
    "normal",
    "ground"
  ],
  "abilities": [
    {
      "id": "pickup",
      "hidden": false,
      "label": "Pickup",
      "slot": "first"
    },
    {
      "id": "cheekpouch",
      "hidden": false,
      "label": "Cheekpouch",
      "slot": "second"
    },
    {
      "id": "hugepower",
      "hidden": true,
      "label": "Hugepower",
      "slot": "hidden"
    }
  ],
  "eggGroups": [
    "field"
  ],
  "labels": [
    "gen6"
  ],
  "aspects": [],
  "aliases": [
    "diggersby"
  ],
  "maleRatio": 0.5,
  "height": 10,
  "weight": 424,
  "catchRate": 127,
  "baseExperienceYield": 148,
  "baseFriendship": 50,
  "eggCycles": 15,
  "baseStats": {
    "hp": 85,
    "attack": 56,
    "defence": 77,
    "special_attack": 50,
    "special_defence": 77,
    "speed": 78
  },
  "evYield": {
    "hp": 2,
    "attack": 0,
    "defence": 0,
    "special_attack": 0,
    "special_defence": 0,
    "speed": 0
  },
  "preEvolution": {
    "raw": "bunnelby",
    "slug": "bunnelby",
    "aspectTokens": []
  },
  "evolutions": [],
  "evolutionFamily": {
    "members": [
      {
        "nodeId": "bunnelby",
        "slug": "bunnelby",
        "name": "Bunnelby",
        "dexNumber": 659,
        "formSlug": null,
        "formName": null
      },
      {
        "nodeId": "diggersby",
        "slug": "diggersby",
        "name": "Diggersby",
        "dexNumber": 660,
        "formSlug": null,
        "formName": null
      }
    ],
    "edges": [
      {
        "fromNodeId": "bunnelby",
        "toNodeId": "diggersby",
        "fromSlug": "bunnelby",
        "toSlug": "diggersby",
        "method": "level_up",
        "requirementText": [
          "Level 20+"
        ]
      }
    ],
    "roots": [
      "bunnelby"
    ]
  },
  "moves": [
    {
      "raw": "tm:agility",
      "moveId": "agility",
      "moveName": "Agility",
      "type": "psychic",
      "sourceType": "tm",
      "sourceValue": null,
      "fromForm": null,
      "fromFormSlug": null
    },
    {
      "raw": "legacy:attract",
      "moveId": "attract",
      "moveName": "Attract",
      "type": "normal",
      "sourceType": "legacy",
      "sourceValue": null,
      "fromForm": null,
      "fromFormSlug": null
    },
    {
      "raw": "tm:bodyslam",
      "moveId": "bodyslam",
      "moveName": "Body Slam",
      "type": "normal",
      "sourceType": "tm",
      "sourceValue": null,
      "fromForm": null,
      "fromFormSlug": null
    },
    {
      "raw": "33:bounce",
      "moveId": "bounce",
      "moveName": "Bounce",
      "type": "flying",
      "sourceType": "level",
      "sourceValue": 33,
      "fromForm": null,
      "fromFormSlug": null
    },
    {
      "raw": "tm:bounce",
      "moveId": "bounce",
      "moveName": "Bounce",
      "type": "flying",
      "sourceType": "tm",
      "sourceValue": null,
      "fromForm": null,
      "fromFormSlug": null
    },
    {
      "raw": "tutor:bounce",
      "moveId": "bounce",
      "moveName": "Bounce",
      "type": "flying",
      "sourceType": "tutor",
      "sourceValue": null,
      "fromForm": null,
      "fromFormSlug": null
    },
    {
      "raw": "tm:brickbreak",
      "moveId": "brickbreak",
      "moveName": "Brick Break",
      "type": "fighting",
      "sourceType": "tm",
      "sourceValue": null,
      "fromForm": null,
      "fromFormSlug": null
    },
    {
      "raw": "tm:brutalswing",
      "moveId": "brutalswing",
      "moveName": "Brutal Swing",
      "type": "dark",
      "sourceType": "tm",
      "sourceValue": null,
      "fromForm": null,
      "fromFormSlug": null
    },
    {
      "raw": "tm:bulkup",
      "moveId": "bulkup",
      "moveName": "Bulk Up",
      "type": "fighting",
      "sourceType": "tm",
      "sourceValue": null,
      "fromForm": null,
      "fromFormSlug": null
    },
    {
      "raw": "tutor:bulkup",
      "moveId": "bulkup",
      "moveName": "Bulk Up",
      "type": "fighting",
      "sourceType": "tutor",
      "sourceValue": null,
      "fromForm": null,
      "fromFormSlug": null
    },
    {
      "raw": "23:bulldoze",
      "moveId": "bulldoze",
      "moveName": "Bulldoze",
      "type": "ground",
      "sourceType": "level",
      "sourceValue": 23,
      "fromForm": null,
      "fromFormSlug": null
    },
    {
      "raw": "tm:bulldoze",
      "moveId": "bulldoze",
      "moveName": "Bulldoze",
      "type": "ground",
      "sourceType": "tm",
      "sourceValue": null,
      "fromForm": null,
      "fromFormSlug": null
    },
    {
      "raw": "tutor:bulldoze",
      "moveId": "bulldoze",
      "moveName": "Bulldoze",
      "type": "ground",
      "sourceType": "tutor",
      "sourceValue": null,
      "fromForm": null,
      "fromFormSlug": null
    },
    {
      "raw": "legacy:confide",
      "moveId": "confide",
      "moveName": "Confide",
      "type": "normal",
      "sourceType": "legacy",
      "sourceValue": null,
      "fromForm": null,
      "fromFormSlug": null
    },
    {
      "raw": "tm:cut",
      "moveId": "cut",
      "moveName": "Cut",
      "type": "normal",
      "sourceType": "tm",
      "sourceValue": null,
      "fromForm": null,
      "fromFormSlug": null
    },
    {
      "raw": "egg:defensecurl",
      "moveId": "defensecurl",
      "moveName": "Defense Curl",
      "type": "normal",
      "sourceType": "egg",
      "sourceValue": null,
      "fromForm": null,
      "fromFormSlug": null
    },
    {
      "raw": "28:dig",
      "moveId": "dig",
      "moveName": "Dig",
      "type": "ground",
      "sourceType": "level",
      "sourceValue": 28,
      "fromForm": null,
      "fromFormSlug": null
    },
    {
      "raw": "tm:dig",
      "moveId": "dig",
      "moveName": "Dig",
      "type": "ground",
      "sourceType": "tm",
      "sourceValue": null,
      "fromForm": null,
      "fromFormSlug": null
    },
    {
      "raw": "18:doublekick",
      "moveId": "doublekick",
      "moveName": "Double Kick",
      "type": "fighting",
      "sourceType": "level",
      "sourceValue": 18,
      "fromForm": null,
      "fromFormSlug": null
    },
    {
      "raw": "1:doubleslap",
      "moveId": "doubleslap",
      "moveName": "Double Slap",
      "type": "normal",
      "sourceType": "level",
      "sourceValue": 1,
      "fromForm": null,
      "fromFormSlug": null
    },
    {
      "raw": "legacy:doubleteam",
      "moveId": "doubleteam",
      "moveName": "Double Team",
      "type": "normal",
      "sourceType": "legacy",
      "sourceValue": null,
      "fromForm": null,
      "fromFormSlug": null
    },
    {
      "raw": "tm:earthpower",
      "moveId": "earthpower",
      "moveName": "Earth Power",
      "type": "ground",
      "sourceType": "tm",
      "sourceValue": null,
      "fromForm": null,
      "fromFormSlug": null
    },
    {
      "raw": "tutor:earthpower",
      "moveId": "earthpower",
      "moveName": "Earth Power",
      "type": "ground",
      "sourceType": "tutor",
      "sourceValue": null,
      "fromForm": null,
      "fromFormSlug": null
    },
    {
      "raw": "48:earthquake",
      "moveId": "earthquake",
      "moveName": "Earthquake",
      "type": "ground",
      "sourceType": "level",
      "sourceValue": 48,
      "fromForm": null,
      "fromFormSlug": null
    },
    {
      "raw": "tm:earthquake",
      "moveId": "earthquake",
      "moveName": "Earthquake",
      "type": "ground",
      "sourceType": "tm",
      "sourceValue": null,
      "fromForm": null,
      "fromFormSlug": null
    },
    {
      "raw": "tm:endeavor",
      "moveId": "endeavor",
      "moveName": "Endeavor",
      "type": "normal",
      "sourceType": "tm",
      "sourceValue": null,
      "fromForm": null,
      "fromFormSlug": null
    },
    {
      "raw": "tutor:endeavor",
      "moveId": "endeavor",
      "moveName": "Endeavor",
      "type": "normal",
      "sourceType": "tutor",
      "sourceValue": null,
      "fromForm": null,
      "fromFormSlug": null
    },
    {
      "raw": "tm:endure",
      "moveId": "endure",
      "moveName": "Endure",
      "type": "normal",
      "sourceType": "tm",
      "sourceValue": null,
      "fromForm": null,
      "fromFormSlug": null
    },
    {
      "raw": "tm:facade",
      "moveId": "facade",
      "moveName": "Facade",
      "type": "normal",
      "sourceType": "tm",
      "sourceValue": null,
      "fromForm": null,
      "fromFormSlug": null
    },
    {
      "raw": "tm:firepunch",
      "moveId": "firepunch",
      "moveName": "Fire Punch",
      "type": "fire",
      "sourceType": "tm",
      "sourceValue": null,
      "fromForm": null,
      "fromFormSlug": null
    },
    {
      "raw": "tutor:firepunch",
      "moveId": "firepunch",
      "moveName": "Fire Punch",
      "type": "fire",
      "sourceType": "tutor",
      "sourceValue": null,
      "fromForm": null,
      "fromFormSlug": null
    },
    {
      "raw": "15:flail",
      "moveId": "flail",
      "moveName": "Flail",
      "type": "normal",
      "sourceType": "level",
      "sourceValue": 15,
      "fromForm": null,
      "fromFormSlug": null
    },
    {
      "raw": "tm:fling",
      "moveId": "fling",
      "moveName": "Fling",
      "type": "dark",
      "sourceType": "tm",
      "sourceValue": null,
      "fromForm": null,
      "fromFormSlug": null
    },
    {
      "raw": "tm:focuspunch",
      "moveId": "focuspunch",
      "moveName": "Focus Punch",
      "type": "fighting",
      "sourceType": "tm",
      "sourceValue": null,
      "fromForm": null,
      "fromFormSlug": null
    },
    {
      "raw": "tutor:focuspunch",
      "moveId": "focuspunch",
      "moveName": "Focus Punch",
      "type": "fighting",
      "sourceType": "tutor",
      "sourceValue": null,
      "fromForm": null,
      "fromFormSlug": null
    },
    {
      "raw": "tm:foulplay",
      "moveId": "foulplay",
      "moveName": "Foul Play",
      "type": "dark",
      "sourceType": "tm",
      "sourceValue": null,
      "fromForm": null,
      "fromFormSlug": null
    },
    {
      "raw": "tutor:foulplay",
      "moveId": "foulplay",
      "moveName": "Foul Play",
      "type": "dark",
      "sourceType": "tutor",
      "sourceValue": null,
      "fromForm": null,
      "fromFormSlug": null
    },
    {
      "raw": "legacy:frustration",
      "moveId": "frustration",
      "moveName": "Frustration",
      "type": "normal",
      "sourceType": "legacy",
      "sourceValue": null,
      "fromForm": null,
      "fromFormSlug": null
    },
    {
      "raw": "tm:gastroacid",
      "moveId": "gastroacid",
      "moveName": "Gastro Acid",
      "type": "poison",
      "sourceType": "tm",
      "sourceValue": null,
      "fromForm": null,
      "fromFormSlug": null
    },
    {
      "raw": "tutor:gastroacid",
      "moveId": "gastroacid",
      "moveName": "Gastro Acid",
      "type": "poison",
      "sourceType": "tutor",
      "sourceValue": null,
      "fromForm": null,
      "fromFormSlug": null
    },
    {
      "raw": "tm:gigaimpact",
      "moveId": "gigaimpact",
      "moveName": "Giga Impact",
      "type": "normal",
      "sourceType": "tm",
      "sourceValue": null,
      "fromForm": null,
      "fromFormSlug": null
    },
    {
      "raw": "tutor:gigaimpact",
      "moveId": "gigaimpact",
      "moveName": "Giga Impact",
      "type": "normal",
      "sourceType": "tutor",
      "sourceValue": null,
      "fromForm": null,
      "fromFormSlug": null
    },
    {
      "raw": "tm:grassknot",
      "moveId": "grassknot",
      "moveName": "Grass Knot",
      "type": "grass",
      "sourceType": "tm",
      "sourceValue": null,
      "fromForm": null,
      "fromFormSlug": null
    },
    {
      "raw": "tm:gunkshot",
      "moveId": "gunkshot",
      "moveName": "Gunk Shot",
      "type": "poison",
      "sourceType": "tm",
      "sourceValue": null,
      "fromForm": null,
      "fromFormSlug": null
    },
    {
      "raw": "tutor:gunkshot",
      "moveId": "gunkshot",
      "moveName": "Gunk Shot",
      "type": "poison",
      "sourceType": "tutor",
      "sourceValue": null,
      "fromForm": null,
      "fromFormSlug": null
    },
    {
      "raw": "58:hammerarm",
      "moveId": "hammerarm",
      "moveName": "Hammer Arm",
      "type": "fighting",
      "sourceType": "level",
      "sourceValue": 58,
      "fromForm": null,
      "fromFormSlug": null
    },
    {
      "raw": "legacy:hiddenpower",
      "moveId": "hiddenpower",
      "moveName": "Hidden Power",
      "type": "normal",
      "sourceType": "legacy",
      "sourceValue": null,
      "fromForm": null,
      "fromFormSlug": null
    },
    {
      "raw": "tm:highhorsepower",
      "moveId": "highhorsepower",
      "moveName": "High Horsepower",
      "type": "ground",
      "sourceType": "tm",
      "sourceValue": null,
      "fromForm": null,
      "fromFormSlug": null
    },
    {
      "raw": "tutor:highhorsepower",
      "moveId": "highhorsepower",
      "moveName": "High Horsepower",
      "type": "ground",
      "sourceType": "tutor",
      "sourceValue": null,
      "fromForm": null,
      "fromFormSlug": null
    },
    {
      "raw": "tm:hyperbeam",
      "moveId": "hyperbeam",
      "moveName": "Hyper Beam",
      "type": "normal",
      "sourceType": "tm",
      "sourceValue": null,
      "fromForm": null,
      "fromFormSlug": null
    },
    {
      "raw": "tutor:hyperbeam",
      "moveId": "hyperbeam",
      "moveName": "Hyper Beam",
      "type": "normal",
      "sourceType": "tutor",
      "sourceValue": null,
      "fromForm": null,
      "fromFormSlug": null
    },
    {
      "raw": "tm:icepunch",
      "moveId": "icepunch",
      "moveName": "Ice Punch",
      "type": "ice",
      "sourceType": "tm",
      "sourceValue": null,
      "fromForm": null,
      "fromFormSlug": null
    },
    {
      "raw": "tutor:icepunch",
      "moveId": "icepunch",
      "moveName": "Ice Punch",
      "type": "ice",
      "sourceType": "tutor",
      "sourceValue": null,
      "fromForm": null,
      "fromFormSlug": null
    },
    {
      "raw": "tm:ironhead",
      "moveId": "ironhead",
      "moveName": "Iron Head",
      "type": "steel",
      "sourceType": "tm",
      "sourceValue": null,
      "fromForm": null,
      "fromFormSlug": null
    },
    {
      "raw": "tutor:ironhead",
      "moveId": "ironhead",
      "moveName": "Iron Head",
      "type": "steel",
      "sourceType": "tutor",
      "sourceValue": null,
      "fromForm": null,
      "fromFormSlug": null
    },
    {
      "raw": "tm:irontail",
      "moveId": "irontail",
      "moveName": "Iron Tail",
      "type": "steel",
      "sourceType": "tm",
      "sourceValue": null,
      "fromForm": null,
      "fromFormSlug": null
    },
    {
      "raw": "tutor:irontail",
      "moveId": "irontail",
      "moveName": "Iron Tail",
      "type": "steel",
      "sourceType": "tutor",
      "sourceValue": null,
      "fromForm": null,
      "fromFormSlug": null
    },
    {
      "raw": "tm:knockoff",
      "moveId": "knockoff",
      "moveName": "Knock Off",
      "type": "dark",
      "sourceType": "tm",
      "sourceValue": null,
      "fromForm": null,
      "fromFormSlug": null
    },
    {
      "raw": "tutor:knockoff",
      "moveId": "knockoff",
      "moveName": "Knock Off",
      "type": "dark",
      "sourceType": "tutor",
      "sourceValue": null,
      "fromForm": null,
      "fromFormSlug": null
    },
    {
      "raw": "1:laserfocus",
      "moveId": "laserfocus",
      "moveName": "Laser Focus",
      "type": "normal",
      "sourceType": "level",
      "sourceValue": 1,
      "fromForm": null,
      "fromFormSlug": null
    },
    {
      "raw": "tm:laserfocus",
      "moveId": "laserfocus",
      "moveName": "Laser Focus",
      "type": "normal",
      "sourceType": "tm",
      "sourceValue": null,
      "fromForm": null,
      "fromFormSlug": null
    },
    {
      "raw": "tutor:laserfocus",
      "moveId": "laserfocus",
      "moveName": "Laser Focus",
      "type": "normal",
      "sourceType": "tutor",
      "sourceValue": null,
      "fromForm": null,
      "fromFormSlug": null
    },
    {
      "raw": "tm:lastresort",
      "moveId": "lastresort",
      "moveName": "Last Resort",
      "type": "normal",
      "sourceType": "tm",
      "sourceValue": null,
      "fromForm": null,
      "fromFormSlug": null
    },
    {
      "raw": "tutor:lastresort",
      "moveId": "lastresort",
      "moveName": "Last Resort",
      "type": "normal",
      "sourceType": "tutor",
      "sourceValue": null,
      "fromForm": null,
      "fromFormSlug": null
    },
    {
      "raw": "1:leer",
      "moveId": "leer",
      "moveName": "Leer",
      "type": "normal",
      "sourceType": "level",
      "sourceValue": 1,
      "fromForm": null,
      "fromFormSlug": null
    },
    {
      "raw": "tm:lowkick",
      "moveId": "lowkick",
      "moveName": "Low Kick",
      "type": "fighting",
      "sourceType": "tm",
      "sourceValue": null,
      "fromForm": null,
      "fromFormSlug": null
    },
    {
      "raw": "tutor:lowkick",
      "moveId": "lowkick",
      "moveName": "Low Kick",
      "type": "fighting",
      "sourceType": "tutor",
      "sourceValue": null,
      "fromForm": null,
      "fromFormSlug": null
    },
    {
      "raw": "tm:megakick",
      "moveId": "megakick",
      "moveName": "Mega Kick",
      "type": "normal",
      "sourceType": "tm",
      "sourceValue": null,
      "fromForm": null,
      "fromFormSlug": null
    },
    {
      "raw": "tm:megapunch",
      "moveId": "megapunch",
      "moveName": "Mega Punch",
      "type": "normal",
      "sourceType": "tm",
      "sourceValue": null,
      "fromForm": null,
      "fromFormSlug": null
    },
    {
      "raw": "12:mudshot",
      "moveId": "mudshot",
      "moveName": "Mud Shot",
      "type": "ground",
      "sourceType": "level",
      "sourceValue": 12,
      "fromForm": null,
      "fromFormSlug": null
    },
    {
      "raw": "tm:mudshot",
      "moveId": "mudshot",
      "moveName": "Mud Shot",
      "type": "ground",
      "sourceType": "tm",
      "sourceValue": null,
      "fromForm": null,
      "fromFormSlug": null
    },
    {
      "raw": "1:mudslap",
      "moveId": "mudslap",
      "moveName": "Mud-Slap",
      "type": "ground",
      "sourceType": "level",
      "sourceValue": 1,
      "fromForm": null,
      "fromFormSlug": null
    },
    {
      "raw": "tm:mudslap",
      "moveId": "mudslap",
      "moveName": "Mud-Slap",
      "type": "ground",
      "sourceType": "tm",
      "sourceValue": null,
      "fromForm": null,
      "fromFormSlug": null
    },
    {
      "raw": "tutor:mudslap",
      "moveId": "mudslap",
      "moveName": "Mud-Slap",
      "type": "ground",
      "sourceType": "tutor",
      "sourceValue": null,
      "fromForm": null,
      "fromFormSlug": null
    },
    {
      "raw": "tm:naturepower",
      "moveId": "naturepower",
      "moveName": "Nature Power",
      "type": "normal",
      "sourceType": "tm",
      "sourceValue": null,
      "fromForm": null,
      "fromFormSlug": null
    },
    {
      "raw": "egg:odorsleuth",
      "moveId": "odorsleuth",
      "moveName": "Odor Sleuth",
      "type": "normal",
      "sourceType": "egg",
      "sourceValue": null,
      "fromForm": null,
      "fromFormSlug": null
    },
    {
      "raw": "1:odorsleuth",
      "moveId": "odorsleuth",
      "moveName": "Odor Sleuth",
      "type": "normal",
      "sourceType": "level",
      "sourceValue": 1,
      "fromForm": null,
      "fromFormSlug": null
    },
    {
      "raw": "tm:payback",
      "moveId": "payback",
      "moveName": "Payback",
      "type": "dark",
      "sourceType": "tm",
      "sourceValue": null,
      "fromForm": null,
      "fromFormSlug": null
    },
    {
      "raw": "tm:poweruppunch",
      "moveId": "poweruppunch",
      "moveName": "Power-Up Punch",
      "type": "fighting",
      "sourceType": "tm",
      "sourceValue": null,
      "fromForm": null,
      "fromFormSlug": null
    },
    {
      "raw": "tm:protect",
      "moveId": "protect",
      "moveName": "Protect",
      "type": "normal",
      "sourceType": "tm",
      "sourceValue": null,
      "fromForm": null,
      "fromFormSlug": null
    },
    {
      "raw": "9:quickattack",
      "moveId": "quickattack",
      "moveName": "Quick Attack",
      "type": "normal",
      "sourceType": "level",
      "sourceValue": 9,
      "fromForm": null,
      "fromFormSlug": null
    },
    {
      "raw": "tm:recycle",
      "moveId": "recycle",
      "moveName": "Recycle",
      "type": "normal",
      "sourceType": "tm",
      "sourceValue": null,
      "fromForm": null,
      "fromFormSlug": null
    },
    {
      "raw": "tutor:recycle",
      "moveId": "recycle",
      "moveName": "Recycle",
      "type": "normal",
      "sourceType": "tutor",
      "sourceValue": null,
      "fromForm": null,
      "fromFormSlug": null
    },
    {
      "raw": "tm:rest",
      "moveId": "rest",
      "moveName": "Rest",
      "type": "psychic",
      "sourceType": "tm",
      "sourceValue": null,
      "fromForm": null,
      "fromFormSlug": null
    },
    {
      "raw": "tutor:rest",
      "moveId": "rest",
      "moveName": "Rest",
      "type": "psychic",
      "sourceType": "tutor",
      "sourceValue": null,
      "fromForm": null,
      "fromFormSlug": null
    },
    {
      "raw": "legacy:return",
      "moveId": "return",
      "moveName": "Return",
      "type": "normal",
      "sourceType": "legacy",
      "sourceValue": null,
      "fromForm": null,
      "fromFormSlug": null
    },
    {
      "raw": "tm:rockslide",
      "moveId": "rockslide",
      "moveName": "Rock Slide",
      "type": "rock",
      "sourceType": "tm",
      "sourceValue": null,
      "fromForm": null,
      "fromFormSlug": null
    },
    {
      "raw": "tutor:rockslide",
      "moveId": "rockslide",
      "moveName": "Rock Slide",
      "type": "rock",
      "sourceType": "tutor",
      "sourceValue": null,
      "fromForm": null,
      "fromFormSlug": null
    },
    {
      "raw": "tm:rocksmash",
      "moveId": "rocksmash",
      "moveName": "Rock Smash",
      "type": "fighting",
      "sourceType": "tm",
      "sourceValue": null,
      "fromForm": null,
      "fromFormSlug": null
    },
    {
      "raw": "tutor:rocksmash",
      "moveId": "rocksmash",
      "moveName": "Rock Smash",
      "type": "fighting",
      "sourceType": "tutor",
      "sourceValue": null,
      "fromForm": null,
      "fromFormSlug": null
    },
    {
      "raw": "tm:rocktomb",
      "moveId": "rocktomb",
      "moveName": "Rock Tomb",
      "type": "rock",
      "sourceType": "tm",
      "sourceValue": null,
      "fromForm": null,
      "fromFormSlug": null
    },
    {
      "raw": "egg:rollout",
      "moveId": "rollout",
      "moveName": "Rollout",
      "type": "rock",
      "sourceType": "egg",
      "sourceValue": null,
      "fromForm": null,
      "fromFormSlug": null
    },
    {
      "raw": "tm:rollout",
      "moveId": "rollout",
      "moveName": "Rollout",
      "type": "rock",
      "sourceType": "tm",
      "sourceValue": null,
      "fromForm": null,
      "fromFormSlug": null
    },
    {
      "raw": "tutor:rollout",
      "moveId": "rollout",
      "moveName": "Rollout",
      "type": "rock",
      "sourceType": "tutor",
      "sourceValue": null,
      "fromForm": null,
      "fromFormSlug": null
    },
    {
      "raw": "1:rototiller",
      "moveId": "rototiller",
      "moveName": "Rototiller",
      "type": "ground",
      "sourceType": "level",
      "sourceValue": 1,
      "fromForm": null,
      "fromFormSlug": null
    },
    {
      "raw": "legacy:round",
      "moveId": "round",
      "moveName": "Round",
      "type": "normal",
      "sourceType": "legacy",
      "sourceValue": null,
      "fromForm": null,
      "fromFormSlug": null
    },
    {
      "raw": "tm:sandtomb",
      "moveId": "sandtomb",
      "moveName": "Sand Tomb",
      "type": "ground",
      "sourceType": "tm",
      "sourceValue": null,
      "fromForm": null,
      "fromFormSlug": null
    },
    {
      "raw": "tm:sandstorm",
      "moveId": "sandstorm",
      "moveName": "Sandstorm",
      "type": "rock",
      "sourceType": "tm",
      "sourceValue": null,
      "fromForm": null,
      "fromFormSlug": null
    },
    {
      "raw": "tm:scorchingsands",
      "moveId": "scorchingsands",
      "moveName": "Scorching Sands",
      "type": "ground",
      "sourceType": "tm",
      "sourceValue": null,
      "fromForm": null,
      "fromFormSlug": null
    },
    {
      "raw": "tutor:scorchingsands",
      "moveId": "scorchingsands",
      "moveName": "Scorching Sands",
      "type": "ground",
      "sourceType": "tutor",
      "sourceValue": null,
      "fromForm": null,
      "fromFormSlug": null
    },
    {
      "raw": "legacy:secretpower",
      "moveId": "secretpower",
      "moveName": "Secret Power",
      "type": "normal",
      "sourceType": "legacy",
      "sourceValue": null,
      "fromForm": null,
      "fromFormSlug": null
    },
    {
      "raw": "tm:sleeptalk",
      "moveId": "sleeptalk",
      "moveName": "Sleep Talk",
      "type": "normal",
      "sourceType": "tm",
      "sourceValue": null,
      "fromForm": null,
      "fromFormSlug": null
    },
    {
      "raw": "tutor:sleeptalk",
      "moveId": "sleeptalk",
      "moveName": "Sleep Talk",
      "type": "normal",
      "sourceType": "tutor",
      "sourceValue": null,
      "fromForm": null,
      "fromFormSlug": null
    },
    {
      "raw": "tm:sludgebomb",
      "moveId": "sludgebomb",
      "moveName": "Sludge Bomb",
      "type": "poison",
      "sourceType": "tm",
      "sourceValue": null,
      "fromForm": null,
      "fromFormSlug": null
    },
    {
      "raw": "tutor:sludgebomb",
      "moveId": "sludgebomb",
      "moveName": "Sludge Bomb",
      "type": "poison",
      "sourceType": "tutor",
      "sourceValue": null,
      "fromForm": null,
      "fromFormSlug": null
    },
    {
      "raw": "tm:smackdown",
      "moveId": "smackdown",
      "moveName": "Smack Down",
      "type": "rock",
      "sourceType": "tm",
      "sourceValue": null,
      "fromForm": null,
      "fromFormSlug": null
    },
    {
      "raw": "tm:snatch",
      "moveId": "snatch",
      "moveName": "Snatch",
      "type": "dark",
      "sourceType": "tm",
      "sourceValue": null,
      "fromForm": null,
      "fromFormSlug": null
    },
    {
      "raw": "tutor:snatch",
      "moveId": "snatch",
      "moveName": "Snatch",
      "type": "dark",
      "sourceType": "tutor",
      "sourceValue": null,
      "fromForm": null,
      "fromFormSlug": null
    },
    {
      "raw": "legacy:snore",
      "moveId": "snore",
      "moveName": "Snore",
      "type": "normal",
      "sourceType": "legacy",
      "sourceValue": null,
      "fromForm": null,
      "fromFormSlug": null
    },
    {
      "raw": "tm:spikes",
      "moveId": "spikes",
      "moveName": "Spikes",
      "type": "ground",
      "sourceType": "tm",
      "sourceValue": null,
      "fromForm": null,
      "fromFormSlug": null
    },
    {
      "raw": "tutor:spikes",
      "moveId": "spikes",
      "moveName": "Spikes",
      "type": "ground",
      "sourceType": "tutor",
      "sourceValue": null,
      "fromForm": null,
      "fromFormSlug": null
    },
    {
      "raw": "tm:stompingtantrum",
      "moveId": "stompingtantrum",
      "moveName": "Stomping Tantrum",
      "type": "ground",
      "sourceType": "tm",
      "sourceValue": null,
      "fromForm": null,
      "fromFormSlug": null
    },
    {
      "raw": "tutor:stompingtantrum",
      "moveId": "stompingtantrum",
      "moveName": "Stomping Tantrum",
      "type": "ground",
      "sourceType": "tutor",
      "sourceValue": null,
      "fromForm": null,
      "fromFormSlug": null
    },
    {
      "raw": "tm:stoneedge",
      "moveId": "stoneedge",
      "moveName": "Stone Edge",
      "type": "rock",
      "sourceType": "tm",
      "sourceValue": null,
      "fromForm": null,
      "fromFormSlug": null
    },
    {
      "raw": "tutor:stoneedge",
      "moveId": "stoneedge",
      "moveName": "Stone Edge",
      "type": "rock",
      "sourceType": "tutor",
      "sourceValue": null,
      "fromForm": null,
      "fromFormSlug": null
    },
    {
      "raw": "tm:strength",
      "moveId": "strength",
      "moveName": "Strength",
      "type": "normal",
      "sourceType": "tm",
      "sourceValue": null,
      "fromForm": null,
      "fromFormSlug": null
    },
    {
      "raw": "tm:substitute",
      "moveId": "substitute",
      "moveName": "Substitute",
      "type": "normal",
      "sourceType": "tm",
      "sourceValue": null,
      "fromForm": null,
      "fromFormSlug": null
    },
    {
      "raw": "53:superfang",
      "moveId": "superfang",
      "moveName": "Super Fang",
      "type": "normal",
      "sourceType": "level",
      "sourceValue": 53,
      "fromForm": null,
      "fromFormSlug": null
    },
    {
      "raw": "tm:superfang",
      "moveId": "superfang",
      "moveName": "Super Fang",
      "type": "normal",
      "sourceType": "tm",
      "sourceValue": null,
      "fromForm": null,
      "fromFormSlug": null
    },
    {
      "raw": "tutor:superfang",
      "moveId": "superfang",
      "moveName": "Super Fang",
      "type": "normal",
      "sourceType": "tutor",
      "sourceValue": null,
      "fromForm": null,
      "fromFormSlug": null
    },
    {
      "raw": "tm:superpower",
      "moveId": "superpower",
      "moveName": "Superpower",
      "type": "fighting",
      "sourceType": "tm",
      "sourceValue": null,
      "fromForm": null,
      "fromFormSlug": null
    },
    {
      "raw": "tutor:superpower",
      "moveId": "superpower",
      "moveName": "Superpower",
      "type": "fighting",
      "sourceType": "tutor",
      "sourceValue": null,
      "fromForm": null,
      "fromFormSlug": null
    },
    {
      "raw": "tm:surf",
      "moveId": "surf",
      "moveName": "Surf",
      "type": "water",
      "sourceType": "tm",
      "sourceValue": null,
      "fromForm": null,
      "fromFormSlug": null
    },
    {
      "raw": "legacy:swagger",
      "moveId": "swagger",
      "moveName": "Swagger",
      "type": "normal",
      "sourceType": "legacy",
      "sourceValue": null,
      "fromForm": null,
      "fromFormSlug": null
    },
    {
      "raw": "43:swordsdance",
      "moveId": "swordsdance",
      "moveName": "Swords Dance",
      "type": "normal",
      "sourceType": "level",
      "sourceValue": 43,
      "fromForm": null,
      "fromFormSlug": null
    },
    {
      "raw": "tm:swordsdance",
      "moveId": "swordsdance",
      "moveName": "Swords Dance",
      "type": "normal",
      "sourceType": "tm",
      "sourceValue": null,
      "fromForm": null,
      "fromFormSlug": null
    },
    {
      "raw": "1:tackle",
      "moveId": "tackle",
      "moveName": "Tackle",
      "type": "normal",
      "sourceType": "level",
      "sourceValue": 1,
      "fromForm": null,
      "fromFormSlug": null
    },
    {
      "raw": "38:takedown",
      "moveId": "takedown",
      "moveName": "Take Down",
      "type": "normal",
      "sourceType": "level",
      "sourceValue": 38,
      "fromForm": null,
      "fromFormSlug": null
    },
    {
      "raw": "tm:takedown",
      "moveId": "takedown",
      "moveName": "Take Down",
      "type": "normal",
      "sourceType": "tm",
      "sourceValue": null,
      "fromForm": null,
      "fromFormSlug": null
    },
    {
      "raw": "tm:terablast",
      "moveId": "terablast",
      "moveName": "Tera Blast",
      "type": "normal",
      "sourceType": "tm",
      "sourceValue": null,
      "fromForm": null,
      "fromFormSlug": null
    },
    {
      "raw": "tm:thief",
      "moveId": "thief",
      "moveName": "Thief",
      "type": "dark",
      "sourceType": "tm",
      "sourceValue": null,
      "fromForm": null,
      "fromFormSlug": null
    },
    {
      "raw": "tm:thunderpunch",
      "moveId": "thunderpunch",
      "moveName": "Thunder Punch",
      "type": "electric",
      "sourceType": "tm",
      "sourceValue": null,
      "fromForm": null,
      "fromFormSlug": null
    },
    {
      "raw": "tutor:thunderpunch",
      "moveId": "thunderpunch",
      "moveName": "Thunder Punch",
      "type": "electric",
      "sourceType": "tutor",
      "sourceValue": null,
      "fromForm": null,
      "fromFormSlug": null
    },
    {
      "raw": "tm:torment",
      "moveId": "torment",
      "moveName": "Torment",
      "type": "dark",
      "sourceType": "tm",
      "sourceValue": null,
      "fromForm": null,
      "fromFormSlug": null
    },
    {
      "raw": "legacy:toxic",
      "moveId": "toxic",
      "moveName": "Toxic",
      "type": "poison",
      "sourceType": "legacy",
      "sourceValue": null,
      "fromForm": null,
      "fromFormSlug": null
    },
    {
      "raw": "tm:uturn",
      "moveId": "uturn",
      "moveName": "U-turn",
      "type": "bug",
      "sourceType": "tm",
      "sourceValue": null,
      "fromForm": null,
      "fromFormSlug": null
    },
    {
      "raw": "tm:uproar",
      "moveId": "uproar",
      "moveName": "Uproar",
      "type": "normal",
      "sourceType": "tm",
      "sourceValue": null,
      "fromForm": null,
      "fromFormSlug": null
    },
    {
      "raw": "tutor:uproar",
      "moveId": "uproar",
      "moveName": "Uproar",
      "type": "normal",
      "sourceType": "tutor",
      "sourceValue": null,
      "fromForm": null,
      "fromFormSlug": null
    },
    {
      "raw": "tm:wildcharge",
      "moveId": "wildcharge",
      "moveName": "Wild Charge",
      "type": "electric",
      "sourceType": "tm",
      "sourceValue": null,
      "fromForm": null,
      "fromFormSlug": null
    },
    {
      "raw": "tutor:wildcharge",
      "moveId": "wildcharge",
      "moveName": "Wild Charge",
      "type": "electric",
      "sourceType": "tutor",
      "sourceValue": null,
      "fromForm": null,
      "fromFormSlug": null
    },
    {
      "raw": "tm:workup",
      "moveId": "workup",
      "moveName": "Work Up",
      "type": "normal",
      "sourceType": "tm",
      "sourceValue": null,
      "fromForm": null,
      "fromFormSlug": null
    }
  ],
  "spawnEntries": [
    {
      "id": "diggersby-1",
      "sourceFile": "0660_diggersby.json",
      "pokemon": {
        "raw": "diggersby",
        "slug": "diggersby",
        "aspectTokens": []
      },
      "type": "pokemon",
      "spawnablePositionType": "grounded",
      "bucket": "common",
      "bucketWeight": 94.3,
      "levelText": "20-42",
      "levelMin": 20,
      "levelMax": 42,
      "weight": 0.6,
      "presets": [
        "natural"
      ],
      "biomeHints": [
        "Is Hills",
        "Is Hill",
        "Is Highlands",
        "Is Temperate",
        "Is Forest",
        "Is Plains"
      ],
      "condition": {
        "neededBaseBlocks": [
          "#cobblemon:natural"
        ],
        "biomes": [
          "#cobblemon:is_hills",
          "#cobblemon:is_temperate"
        ],
        "minY": 32
      },
      "anticondition": {
        "neededBaseBlocks": [
          "minecraft:farmland"
        ]
      },
      "weightMultipliers": [],
      "raw": {
        "id": "diggersby-1",
        "pokemon": "diggersby",
        "presets": [
          "natural"
        ],
        "type": "pokemon",
        "spawnablePositionType": "grounded",
        "bucket": "common",
        "level": "20-42",
        "weight": 0.6,
        "condition": {
          "biomes": [
            "#cobblemon:is_hills",
            "#cobblemon:is_temperate"
          ],
          "minY": 32
        }
      }
    }
  ],
  "forms": [],
  "drops": {
    "amount": 6,
    "entries": [
      {
        "item": "minecraft:rabbit"
      },
      {
        "item": "minecraft:rabbit_hide",
        "quantityRange": "0-2"
      },
      {
        "item": "minecraft:rabbit_foot",
        "percentage": 5
      },
      {
        "item": "minecraft:carrot",
        "percentage": 5
      },
      {
        "item": "cobblemon:chilan_berry",
        "percentage": 5
      }
    ]
  },
  "rawSpecies": {
    "implemented": true,
    "nationalPokedexNumber": 660,
    "name": "Diggersby",
    "primaryType": "normal",
    "secondaryType": "ground",
    "maleRatio": 0.5,
    "height": 10,
    "weight": 424,
    "pokedex": [
      "cobblemon.species.diggersby.desc"
    ],
    "labels": [
      "gen6"
    ],
    "aspects": [],
    "abilities": [
      "pickup",
      "cheekpouch",
      "h:hugepower"
    ],
    "eggGroups": [
      "field"
    ],
    "baseStats": {
      "hp": 85,
      "attack": 56,
      "defence": 77,
      "special_attack": 50,
      "special_defence": 77,
      "speed": 78
    },
    "evYield": {
      "hp": 2,
      "attack": 0,
      "defence": 0,
      "special_attack": 0,
      "special_defence": 0,
      "speed": 0
    },
    "baseExperienceYield": 148,
    "experienceGroup": "medium_fast",
    "catchRate": 127,
    "eggCycles": 15,
    "baseFriendship": 50,
    "baseScale": 0.8,
    "hitbox": {
      "width": 1.25,
      "height": 2.2,
      "fixed": false
    },
    "behaviour": {
      "moving": {
        "walk": {
          "walkSpeed": 0.2
        },
        "swim": {
          "avoidsWater": true
        }
      },
      "resting": {
        "canSleep": true,
        "light": "0-4",
        "drowsyChance": 0.0333,
        "rouseChance": 0.0042
      },
      "herd": {
        "maxSize": "5",
        "toleratedLeaders": [
          {
            "pokemon": "diggersby",
            "tier": 1
          }
        ]
      },
      "combat": {
        "willDefendOwner": true
      }
    },
    "drops": {
      "amount": 6,
      "entries": [
        {
          "item": "minecraft:rabbit"
        },
        {
          "item": "minecraft:rabbit_hide",
          "quantityRange": "0-2"
        },
        {
          "item": "minecraft:rabbit_foot",
          "percentage": 5
        },
        {
          "item": "minecraft:carrot",
          "percentage": 5
        },
        {
          "item": "cobblemon:chilan_berry",
          "percentage": 5
        }
      ]
    },
    "moves": [
      "1:rototiller",
      "1:tackle",
      "1:leer",
      "1:mudslap",
      "1:odorsleuth",
      "1:doubleslap",
      "1:laserfocus",
      "9:quickattack",
      "12:mudshot",
      "15:flail",
      "18:doublekick",
      "23:bulldoze",
      "28:dig",
      "33:bounce",
      "38:takedown",
      "43:swordsdance",
      "48:earthquake",
      "53:superfang",
      "58:hammerarm",
      "egg:defensecurl",
      "egg:odorsleuth",
      "egg:rollout",
      "tm:agility",
      "tm:bodyslam",
      "tm:bounce",
      "tm:brickbreak",
      "tm:brutalswing",
      "tm:bulkup",
      "tm:bulldoze",
      "tm:cut",
      "tm:dig",
      "tm:earthpower",
      "tm:earthquake",
      "tm:endeavor",
      "tm:endure",
      "tm:facade",
      "tm:firepunch",
      "tm:fling",
      "tm:focuspunch",
      "tm:foulplay",
      "tm:gastroacid",
      "tm:gigaimpact",
      "tm:grassknot",
      "tm:gunkshot",
      "tm:highhorsepower",
      "tm:hyperbeam",
      "tm:icepunch",
      "tm:ironhead",
      "tm:irontail",
      "tm:knockoff",
      "tm:laserfocus",
      "tm:lastresort",
      "tm:lowkick",
      "tm:megakick",
      "tm:megapunch",
      "tm:mudshot",
      "tm:mudslap",
      "tm:naturepower",
      "tm:payback",
      "tm:poweruppunch",
      "tm:protect",
      "tm:recycle",
      "tm:rest",
      "tm:rockslide",
      "tm:rocksmash",
      "tm:rocktomb",
      "tm:rollout",
      "tm:sandstorm",
      "tm:sandtomb",
      "tm:scorchingsands",
      "tm:sleeptalk",
      "tm:sludgebomb",
      "tm:smackdown",
      "tm:snatch",
      "tm:spikes",
      "tm:stompingtantrum",
      "tm:stoneedge",
      "tm:strength",
      "tm:substitute",
      "tm:superfang",
      "tm:superpower",
      "tm:surf",
      "tm:swordsdance",
      "tm:takedown",
      "tm:terablast",
      "tm:thief",
      "tm:thunderpunch",
      "tm:torment",
      "tm:uproar",
      "tm:uturn",
      "tm:wildcharge",
      "tm:workup",
      "tutor:bounce",
      "tutor:bulkup",
      "tutor:bulldoze",
      "tutor:earthpower",
      "tutor:endeavor",
      "tutor:firepunch",
      "tutor:focuspunch",
      "tutor:foulplay",
      "tutor:gastroacid",
      "tutor:gigaimpact",
      "tutor:gunkshot",
      "tutor:highhorsepower",
      "tutor:hyperbeam",
      "tutor:icepunch",
      "tutor:ironhead",
      "tutor:irontail",
      "tutor:knockoff",
      "tutor:laserfocus",
      "tutor:lastresort",
      "tutor:lowkick",
      "tutor:mudslap",
      "tutor:recycle",
      "tutor:rest",
      "tutor:rockslide",
      "tutor:rocksmash",
      "tutor:rollout",
      "tutor:scorchingsands",
      "tutor:sleeptalk",
      "tutor:sludgebomb",
      "tutor:snatch",
      "tutor:spikes",
      "tutor:stompingtantrum",
      "tutor:stoneedge",
      "tutor:superfang",
      "tutor:superpower",
      "tutor:thunderpunch",
      "tutor:uproar",
      "tutor:wildcharge",
      "legacy:attract",
      "legacy:confide",
      "legacy:doubleteam",
      "legacy:frustration",
      "legacy:hiddenpower",
      "legacy:return",
      "legacy:round",
      "legacy:secretpower",
      "legacy:snore",
      "legacy:swagger",
      "legacy:toxic"
    ],
    "preEvolution": "bunnelby",
    "evolutions": []
  }
}
