{
  "slug": "orbeetle",
  "name": "Orbeetle",
  "dexNumber": 826,
  "implemented": false,
  "types": [
    "bug",
    "psychic"
  ],
  "abilities": [
    {
      "id": "swarm",
      "hidden": false,
      "label": "Swarm",
      "slot": "first"
    },
    {
      "id": "frisk",
      "hidden": false,
      "label": "Frisk",
      "slot": "second"
    },
    {
      "id": "telepathy",
      "hidden": true,
      "label": "Telepathy",
      "slot": "hidden"
    }
  ],
  "eggGroups": [
    "bug"
  ],
  "labels": [
    "gen8"
  ],
  "aspects": [],
  "aliases": [
    "gmax",
    "orbeetle",
    "orbeetle gmax"
  ],
  "maleRatio": 0.5,
  "height": 4,
  "weight": 408,
  "catchRate": 45,
  "baseExperienceYield": 253,
  "baseFriendship": 50,
  "eggCycles": 15,
  "baseStats": {
    "hp": 60,
    "attack": 45,
    "defence": 110,
    "special_attack": 80,
    "special_defence": 120,
    "speed": 90
  },
  "evYield": {
    "hp": 0,
    "attack": 0,
    "defence": 0,
    "special_attack": 0,
    "special_defence": 3,
    "speed": 0
  },
  "preEvolution": {
    "raw": "dottler",
    "slug": "dottler",
    "aspectTokens": []
  },
  "evolutions": [],
  "evolutionFamily": {
    "members": [
      {
        "slug": "blipbug",
        "name": "Blipbug",
        "dexNumber": 824
      },
      {
        "slug": "dottler",
        "name": "Dottler",
        "dexNumber": 825
      },
      {
        "slug": "orbeetle",
        "name": "Orbeetle",
        "dexNumber": 826
      }
    ],
    "edges": [
      {
        "fromSlug": "blipbug",
        "toSlug": "dottler",
        "method": "level_up",
        "requirementText": [
          "Level 10+"
        ]
      },
      {
        "fromSlug": "dottler",
        "toSlug": "orbeetle",
        "method": "level_up",
        "requirementText": [
          "Level 30+"
        ]
      }
    ],
    "roots": [
      "blipbug"
    ]
  },
  "moves": [
    {
      "raw": "40:afteryou",
      "moveId": "afteryou",
      "moveName": "After You",
      "type": "normal",
      "sourceType": "level",
      "sourceValue": 40,
      "fromForm": null,
      "fromFormSlug": null
    },
    {
      "raw": "tm:afteryou",
      "moveId": "afteryou",
      "moveName": "After You",
      "type": "normal",
      "sourceType": "tm",
      "sourceValue": null,
      "fromForm": null,
      "fromFormSlug": null
    },
    {
      "raw": "tutor:afteryou",
      "moveId": "afteryou",
      "moveName": "After You",
      "type": "normal",
      "sourceType": "tutor",
      "sourceValue": null,
      "fromForm": null,
      "fromFormSlug": null
    },
    {
      "raw": "12:agility",
      "moveId": "agility",
      "moveName": "Agility",
      "type": "psychic",
      "sourceType": "level",
      "sourceValue": 12,
      "fromForm": null,
      "fromFormSlug": null
    },
    {
      "raw": "tm:agility",
      "moveId": "agility",
      "moveName": "Agility",
      "type": "psychic",
      "sourceType": "tm",
      "sourceValue": null,
      "fromForm": null,
      "fromFormSlug": null
    },
    {
      "raw": "24:allyswitch",
      "moveId": "allyswitch",
      "moveName": "Ally Switch",
      "type": "psychic",
      "sourceType": "level",
      "sourceValue": 24,
      "fromForm": null,
      "fromFormSlug": null
    },
    {
      "raw": "tm:allyswitch",
      "moveId": "allyswitch",
      "moveName": "Ally Switch",
      "type": "psychic",
      "sourceType": "tm",
      "sourceValue": null,
      "fromForm": null,
      "fromFormSlug": null
    },
    {
      "raw": "tutor:allyswitch",
      "moveId": "allyswitch",
      "moveName": "Ally Switch",
      "type": "psychic",
      "sourceType": "tutor",
      "sourceValue": null,
      "fromForm": null,
      "fromFormSlug": null
    },
    {
      "raw": "legacy:attract",
      "moveId": "attract",
      "moveName": "Attract",
      "type": "normal",
      "sourceType": "legacy",
      "sourceValue": null,
      "fromForm": null,
      "fromFormSlug": null
    },
    {
      "raw": "tm:batonpass",
      "moveId": "batonpass",
      "moveName": "Baton Pass",
      "type": "normal",
      "sourceType": "tm",
      "sourceValue": null,
      "fromForm": null,
      "fromFormSlug": null
    },
    {
      "raw": "tm:bodypress",
      "moveId": "bodypress",
      "moveName": "Body Press",
      "type": "fighting",
      "sourceType": "tm",
      "sourceValue": null,
      "fromForm": null,
      "fromFormSlug": null
    },
    {
      "raw": "28:bugbuzz",
      "moveId": "bugbuzz",
      "moveName": "Bug Buzz",
      "type": "bug",
      "sourceType": "level",
      "sourceValue": 28,
      "fromForm": null,
      "fromFormSlug": null
    },
    {
      "raw": "tm:bugbuzz",
      "moveId": "bugbuzz",
      "moveName": "Bug Buzz",
      "type": "bug",
      "sourceType": "tm",
      "sourceValue": null,
      "fromForm": null,
      "fromFormSlug": null
    },
    {
      "raw": "44:calmmind",
      "moveId": "calmmind",
      "moveName": "Calm Mind",
      "type": "psychic",
      "sourceType": "level",
      "sourceValue": 44,
      "fromForm": null,
      "fromFormSlug": null
    },
    {
      "raw": "tm:calmmind",
      "moveId": "calmmind",
      "moveName": "Calm Mind",
      "type": "psychic",
      "sourceType": "tm",
      "sourceValue": null,
      "fromForm": null,
      "fromFormSlug": null
    },
    {
      "raw": "tutor:calmmind",
      "moveId": "calmmind",
      "moveName": "Calm Mind",
      "type": "psychic",
      "sourceType": "tutor",
      "sourceValue": null,
      "fromForm": null,
      "fromFormSlug": null
    },
    {
      "raw": "4:confuseray",
      "moveId": "confuseray",
      "moveName": "Confuse Ray",
      "type": "ghost",
      "sourceType": "level",
      "sourceValue": 4,
      "fromForm": null,
      "fromFormSlug": null
    },
    {
      "raw": "tm:confuseray",
      "moveId": "confuseray",
      "moveName": "Confuse Ray",
      "type": "ghost",
      "sourceType": "tm",
      "sourceValue": null,
      "fromForm": null,
      "fromFormSlug": null
    },
    {
      "raw": "1:confusion",
      "moveId": "confusion",
      "moveName": "Confusion",
      "type": "psychic",
      "sourceType": "level",
      "sourceValue": 1,
      "fromForm": null,
      "fromFormSlug": null
    },
    {
      "raw": "tm:endure",
      "moveId": "endure",
      "moveName": "Endure",
      "type": "normal",
      "sourceType": "tm",
      "sourceValue": null,
      "fromForm": null,
      "fromFormSlug": null
    },
    {
      "raw": "tm:energyball",
      "moveId": "energyball",
      "moveName": "Energy Ball",
      "type": "grass",
      "sourceType": "tm",
      "sourceValue": null,
      "fromForm": null,
      "fromFormSlug": null
    },
    {
      "raw": "tutor:energyball",
      "moveId": "energyball",
      "moveName": "Energy Ball",
      "type": "grass",
      "sourceType": "tutor",
      "sourceValue": null,
      "fromForm": null,
      "fromFormSlug": null
    },
    {
      "raw": "tm:expandingforce",
      "moveId": "expandingforce",
      "moveName": "Expanding Force",
      "type": "psychic",
      "sourceType": "tm",
      "sourceValue": null,
      "fromForm": null,
      "fromFormSlug": null
    },
    {
      "raw": "tutor:expandingforce",
      "moveId": "expandingforce",
      "moveName": "Expanding Force",
      "type": "psychic",
      "sourceType": "tutor",
      "sourceValue": null,
      "fromForm": null,
      "fromFormSlug": null
    },
    {
      "raw": "tm:facade",
      "moveId": "facade",
      "moveName": "Facade",
      "type": "normal",
      "sourceType": "tm",
      "sourceValue": null,
      "fromForm": null,
      "fromFormSlug": null
    },
    {
      "raw": "tm:futuresight",
      "moveId": "futuresight",
      "moveName": "Future Sight",
      "type": "psychic",
      "sourceType": "tm",
      "sourceValue": null,
      "fromForm": null,
      "fromFormSlug": null
    },
    {
      "raw": "tm:gigadrain",
      "moveId": "gigadrain",
      "moveName": "Giga Drain",
      "type": "grass",
      "sourceType": "tm",
      "sourceValue": null,
      "fromForm": null,
      "fromFormSlug": null
    },
    {
      "raw": "tutor:gigadrain",
      "moveId": "gigadrain",
      "moveName": "Giga Drain",
      "type": "grass",
      "sourceType": "tutor",
      "sourceValue": null,
      "fromForm": null,
      "fromFormSlug": null
    },
    {
      "raw": "tm:gigaimpact",
      "moveId": "gigaimpact",
      "moveName": "Giga Impact",
      "type": "normal",
      "sourceType": "tm",
      "sourceValue": null,
      "fromForm": null,
      "fromFormSlug": null
    },
    {
      "raw": "tutor:gigaimpact",
      "moveId": "gigaimpact",
      "moveName": "Giga Impact",
      "type": "normal",
      "sourceType": "tutor",
      "sourceValue": null,
      "fromForm": null,
      "fromFormSlug": null
    },
    {
      "raw": "tm:guardswap",
      "moveId": "guardswap",
      "moveName": "Guard Swap",
      "type": "psychic",
      "sourceType": "tm",
      "sourceValue": null,
      "fromForm": null,
      "fromFormSlug": null
    },
    {
      "raw": "tm:helpinghand",
      "moveId": "helpinghand",
      "moveName": "Helping Hand",
      "type": "normal",
      "sourceType": "tm",
      "sourceValue": null,
      "fromForm": null,
      "fromFormSlug": null
    },
    {
      "raw": "tutor:helpinghand",
      "moveId": "helpinghand",
      "moveName": "Helping Hand",
      "type": "normal",
      "sourceType": "tutor",
      "sourceValue": null,
      "fromForm": null,
      "fromFormSlug": null
    },
    {
      "raw": "tm:hyperbeam",
      "moveId": "hyperbeam",
      "moveName": "Hyper Beam",
      "type": "normal",
      "sourceType": "tm",
      "sourceValue": null,
      "fromForm": null,
      "fromFormSlug": null
    },
    {
      "raw": "tutor:hyperbeam",
      "moveId": "hyperbeam",
      "moveName": "Hyper Beam",
      "type": "normal",
      "sourceType": "tutor",
      "sourceValue": null,
      "fromForm": null,
      "fromFormSlug": null
    },
    {
      "raw": "20:hypnosis",
      "moveId": "hypnosis",
      "moveName": "Hypnosis",
      "type": "psychic",
      "sourceType": "level",
      "sourceValue": 20,
      "fromForm": null,
      "fromFormSlug": null
    },
    {
      "raw": "tm:imprison",
      "moveId": "imprison",
      "moveName": "Imprison",
      "type": "psychic",
      "sourceType": "tm",
      "sourceValue": null,
      "fromForm": null,
      "fromFormSlug": null
    },
    {
      "raw": "egg:infestation",
      "moveId": "infestation",
      "moveName": "Infestation",
      "type": "bug",
      "sourceType": "egg",
      "sourceValue": null,
      "fromForm": null,
      "fromFormSlug": null
    },
    {
      "raw": "tm:infestation",
      "moveId": "infestation",
      "moveName": "Infestation",
      "type": "bug",
      "sourceType": "tm",
      "sourceValue": null,
      "fromForm": null,
      "fromFormSlug": null
    },
    {
      "raw": "tm:irondefense",
      "moveId": "irondefense",
      "moveName": "Iron Defense",
      "type": "steel",
      "sourceType": "tm",
      "sourceValue": null,
      "fromForm": null,
      "fromFormSlug": null
    },
    {
      "raw": "tutor:irondefense",
      "moveId": "irondefense",
      "moveName": "Iron Defense",
      "type": "steel",
      "sourceType": "tutor",
      "sourceValue": null,
      "fromForm": null,
      "fromFormSlug": null
    },
    {
      "raw": "tm:leechlife",
      "moveId": "leechlife",
      "moveName": "Leech Life",
      "type": "bug",
      "sourceType": "tm",
      "sourceValue": null,
      "fromForm": null,
      "fromFormSlug": null
    },
    {
      "raw": "tutor:leechlife",
      "moveId": "leechlife",
      "moveName": "Leech Life",
      "type": "bug",
      "sourceType": "tutor",
      "sourceValue": null,
      "fromForm": null,
      "fromFormSlug": null
    },
    {
      "raw": "1:lightscreen",
      "moveId": "lightscreen",
      "moveName": "Light Screen",
      "type": "psychic",
      "sourceType": "level",
      "sourceValue": 1,
      "fromForm": null,
      "fromFormSlug": null
    },
    {
      "raw": "tm:lightscreen",
      "moveId": "lightscreen",
      "moveName": "Light Screen",
      "type": "psychic",
      "sourceType": "tm",
      "sourceValue": null,
      "fromForm": null,
      "fromFormSlug": null
    },
    {
      "raw": "8:magiccoat",
      "moveId": "magiccoat",
      "moveName": "Magic Coat",
      "type": "psychic",
      "sourceType": "level",
      "sourceValue": 8,
      "fromForm": null,
      "fromFormSlug": null
    },
    {
      "raw": "tm:magiccoat",
      "moveId": "magiccoat",
      "moveName": "Magic Coat",
      "type": "psychic",
      "sourceType": "tm",
      "sourceValue": null,
      "fromForm": null,
      "fromFormSlug": null
    },
    {
      "raw": "tutor:magiccoat",
      "moveId": "magiccoat",
      "moveName": "Magic Coat",
      "type": "psychic",
      "sourceType": "tutor",
      "sourceValue": null,
      "fromForm": null,
      "fromFormSlug": null
    },
    {
      "raw": "tm:magicroom",
      "moveId": "magicroom",
      "moveName": "Magic Room",
      "type": "psychic",
      "sourceType": "tm",
      "sourceValue": null,
      "fromForm": null,
      "fromFormSlug": null
    },
    {
      "raw": "tutor:magicroom",
      "moveId": "magicroom",
      "moveName": "Magic Room",
      "type": "psychic",
      "sourceType": "tutor",
      "sourceValue": null,
      "fromForm": null,
      "fromFormSlug": null
    },
    {
      "raw": "32:mirrorcoat",
      "moveId": "mirrorcoat",
      "moveName": "Mirror Coat",
      "type": "psychic",
      "sourceType": "level",
      "sourceValue": 32,
      "fromForm": null,
      "fromFormSlug": null
    },
    {
      "raw": "tm:payback",
      "moveId": "payback",
      "moveName": "Payback",
      "type": "dark",
      "sourceType": "tm",
      "sourceValue": null,
      "fromForm": null,
      "fromFormSlug": null
    },
    {
      "raw": "tm:powerswap",
      "moveId": "powerswap",
      "moveName": "Power Swap",
      "type": "psychic",
      "sourceType": "tm",
      "sourceValue": null,
      "fromForm": null,
      "fromFormSlug": null
    },
    {
      "raw": "tm:protect",
      "moveId": "protect",
      "moveName": "Protect",
      "type": "normal",
      "sourceType": "tm",
      "sourceValue": null,
      "fromForm": null,
      "fromFormSlug": null
    },
    {
      "raw": "16:psybeam",
      "moveId": "psybeam",
      "moveName": "Psybeam",
      "type": "psychic",
      "sourceType": "level",
      "sourceValue": 16,
      "fromForm": null,
      "fromFormSlug": null
    },
    {
      "raw": "tm:psybeam",
      "moveId": "psybeam",
      "moveName": "Psybeam",
      "type": "psychic",
      "sourceType": "tm",
      "sourceValue": null,
      "fromForm": null,
      "fromFormSlug": null
    },
    {
      "raw": "36:psychic",
      "moveId": "psychic",
      "moveName": "Psychic",
      "type": "psychic",
      "sourceType": "level",
      "sourceValue": 36,
      "fromForm": null,
      "fromFormSlug": null
    },
    {
      "raw": "tm:psychic",
      "moveId": "psychic",
      "moveName": "Psychic",
      "type": "psychic",
      "sourceType": "tm",
      "sourceValue": null,
      "fromForm": null,
      "fromFormSlug": null
    },
    {
      "raw": "tutor:psychic",
      "moveId": "psychic",
      "moveName": "Psychic",
      "type": "psychic",
      "sourceType": "tutor",
      "sourceValue": null,
      "fromForm": null,
      "fromFormSlug": null
    },
    {
      "raw": "48:psychicterrain",
      "moveId": "psychicterrain",
      "moveName": "Psychic Terrain",
      "type": "psychic",
      "sourceType": "level",
      "sourceValue": 48,
      "fromForm": null,
      "fromFormSlug": null
    },
    {
      "raw": "tm:psychicterrain",
      "moveId": "psychicterrain",
      "moveName": "Psychic Terrain",
      "type": "psychic",
      "sourceType": "tm",
      "sourceValue": null,
      "fromForm": null,
      "fromFormSlug": null
    },
    {
      "raw": "tm:psychocut",
      "moveId": "psychocut",
      "moveName": "Psycho Cut",
      "type": "psychic",
      "sourceType": "tm",
      "sourceValue": null,
      "fromForm": null,
      "fromFormSlug": null
    },
    {
      "raw": "tutor:psychocut",
      "moveId": "psychocut",
      "moveName": "Psycho Cut",
      "type": "psychic",
      "sourceType": "tutor",
      "sourceValue": null,
      "fromForm": null,
      "fromFormSlug": null
    },
    {
      "raw": "tm:psyshock",
      "moveId": "psyshock",
      "moveName": "Psyshock",
      "type": "psychic",
      "sourceType": "tm",
      "sourceValue": null,
      "fromForm": null,
      "fromFormSlug": null
    },
    {
      "raw": "egg:recover",
      "moveId": "recover",
      "moveName": "Recover",
      "type": "normal",
      "sourceType": "egg",
      "sourceValue": null,
      "fromForm": null,
      "fromFormSlug": null
    },
    {
      "raw": "1:reflect",
      "moveId": "reflect",
      "moveName": "Reflect",
      "type": "psychic",
      "sourceType": "level",
      "sourceValue": 1,
      "fromForm": null,
      "fromFormSlug": null
    },
    {
      "raw": "tm:reflect",
      "moveId": "reflect",
      "moveName": "Reflect",
      "type": "psychic",
      "sourceType": "tm",
      "sourceValue": null,
      "fromForm": null,
      "fromFormSlug": null
    },
    {
      "raw": "tm:rest",
      "moveId": "rest",
      "moveName": "Rest",
      "type": "psychic",
      "sourceType": "tm",
      "sourceValue": null,
      "fromForm": null,
      "fromFormSlug": null
    },
    {
      "raw": "tutor:rest",
      "moveId": "rest",
      "moveName": "Rest",
      "type": "psychic",
      "sourceType": "tutor",
      "sourceValue": null,
      "fromForm": null,
      "fromFormSlug": null
    },
    {
      "raw": "legacy:round",
      "moveId": "round",
      "moveName": "Round",
      "type": "normal",
      "sourceType": "legacy",
      "sourceValue": null,
      "fromForm": null,
      "fromFormSlug": null
    },
    {
      "raw": "tm:safeguard",
      "moveId": "safeguard",
      "moveName": "Safeguard",
      "type": "normal",
      "sourceType": "tm",
      "sourceValue": null,
      "fromForm": null,
      "fromFormSlug": null
    },
    {
      "raw": "tm:shadowball",
      "moveId": "shadowball",
      "moveName": "Shadow Ball",
      "type": "ghost",
      "sourceType": "tm",
      "sourceValue": null,
      "fromForm": null,
      "fromFormSlug": null
    },
    {
      "raw": "tutor:shadowball",
      "moveId": "shadowball",
      "moveName": "Shadow Ball",
      "type": "ghost",
      "sourceType": "tutor",
      "sourceValue": null,
      "fromForm": null,
      "fromFormSlug": null
    },
    {
      "raw": "tm:skillswap",
      "moveId": "skillswap",
      "moveName": "Skill Swap",
      "type": "psychic",
      "sourceType": "tm",
      "sourceValue": null,
      "fromForm": null,
      "fromFormSlug": null
    },
    {
      "raw": "tutor:skillswap",
      "moveId": "skillswap",
      "moveName": "Skill Swap",
      "type": "psychic",
      "sourceType": "tutor",
      "sourceValue": null,
      "fromForm": null,
      "fromFormSlug": null
    },
    {
      "raw": "tm:sleeptalk",
      "moveId": "sleeptalk",
      "moveName": "Sleep Talk",
      "type": "normal",
      "sourceType": "tm",
      "sourceValue": null,
      "fromForm": null,
      "fromFormSlug": null
    },
    {
      "raw": "tutor:sleeptalk",
      "moveId": "sleeptalk",
      "moveName": "Sleep Talk",
      "type": "normal",
      "sourceType": "tutor",
      "sourceValue": null,
      "fromForm": null,
      "fromFormSlug": null
    },
    {
      "raw": "legacy:snore",
      "moveId": "snore",
      "moveName": "Snore",
      "type": "normal",
      "sourceType": "legacy",
      "sourceValue": null,
      "fromForm": null,
      "fromFormSlug": null
    },
    {
      "raw": "tm:solarbeam",
      "moveId": "solarbeam",
      "moveName": "Solar Beam",
      "type": "grass",
      "sourceType": "tm",
      "sourceValue": null,
      "fromForm": null,
      "fromFormSlug": null
    },
    {
      "raw": "egg:stickyweb",
      "moveId": "stickyweb",
      "moveName": "Sticky Web",
      "type": "bug",
      "sourceType": "egg",
      "sourceValue": null,
      "fromForm": null,
      "fromFormSlug": null
    },
    {
      "raw": "tm:storedpower",
      "moveId": "storedpower",
      "moveName": "Stored Power",
      "type": "psychic",
      "sourceType": "tm",
      "sourceValue": null,
      "fromForm": null,
      "fromFormSlug": null
    },
    {
      "raw": "1:strugglebug",
      "moveId": "strugglebug",
      "moveName": "Struggle Bug",
      "type": "bug",
      "sourceType": "level",
      "sourceValue": 1,
      "fromForm": null,
      "fromFormSlug": null
    },
    {
      "raw": "tm:strugglebug",
      "moveId": "strugglebug",
      "moveName": "Struggle Bug",
      "type": "bug",
      "sourceType": "tm",
      "sourceValue": null,
      "fromForm": null,
      "fromFormSlug": null
    },
    {
      "raw": "tm:substitute",
      "moveId": "substitute",
      "moveName": "Substitute",
      "type": "normal",
      "sourceType": "tm",
      "sourceValue": null,
      "fromForm": null,
      "fromFormSlug": null
    },
    {
      "raw": "egg:supersonic",
      "moveId": "supersonic",
      "moveName": "Supersonic",
      "type": "normal",
      "sourceType": "egg",
      "sourceValue": null,
      "fromForm": null,
      "fromFormSlug": null
    },
    {
      "raw": "tm:terablast",
      "moveId": "terablast",
      "moveName": "Tera Blast",
      "type": "normal",
      "sourceType": "tm",
      "sourceValue": null,
      "fromForm": null,
      "fromFormSlug": null
    },
    {
      "raw": "tm:trick",
      "moveId": "trick",
      "moveName": "Trick",
      "type": "psychic",
      "sourceType": "tm",
      "sourceValue": null,
      "fromForm": null,
      "fromFormSlug": null
    },
    {
      "raw": "tutor:trick",
      "moveId": "trick",
      "moveName": "Trick",
      "type": "psychic",
      "sourceType": "tutor",
      "sourceValue": null,
      "fromForm": null,
      "fromFormSlug": null
    },
    {
      "raw": "tm:trickroom",
      "moveId": "trickroom",
      "moveName": "Trick Room",
      "type": "psychic",
      "sourceType": "tm",
      "sourceValue": null,
      "fromForm": null,
      "fromFormSlug": null
    },
    {
      "raw": "tm:uturn",
      "moveId": "uturn",
      "moveName": "U-turn",
      "type": "bug",
      "sourceType": "tm",
      "sourceValue": null,
      "fromForm": null,
      "fromFormSlug": null
    },
    {
      "raw": "tm:wonderroom",
      "moveId": "wonderroom",
      "moveName": "Wonder Room",
      "type": "psychic",
      "sourceType": "tm",
      "sourceValue": null,
      "fromForm": null,
      "fromFormSlug": null
    },
    {
      "raw": "tutor:wonderroom",
      "moveId": "wonderroom",
      "moveName": "Wonder Room",
      "type": "psychic",
      "sourceType": "tutor",
      "sourceValue": null,
      "fromForm": null,
      "fromFormSlug": null
    },
    {
      "raw": "tm:zenheadbutt",
      "moveId": "zenheadbutt",
      "moveName": "Zen Headbutt",
      "type": "psychic",
      "sourceType": "tm",
      "sourceValue": null,
      "fromForm": null,
      "fromFormSlug": null
    },
    {
      "raw": "tutor:zenheadbutt",
      "moveId": "zenheadbutt",
      "moveName": "Zen Headbutt",
      "type": "psychic",
      "sourceType": "tutor",
      "sourceValue": null,
      "fromForm": null,
      "fromFormSlug": null
    }
  ],
  "spawnEntries": [],
  "forms": [
    {
      "name": "Gmax",
      "slug": "orbeetle-gmax",
      "aspects": [
        "gmax"
      ],
      "labels": [
        "gen8",
        "gmax"
      ],
      "types": [
        "bug",
        "psychic"
      ],
      "maleRatio": 0.5,
      "height": 140,
      "weight": 0,
      "catchRate": null,
      "baseExperienceYield": null,
      "baseFriendship": null,
      "eggCycles": null,
      "baseStats": {},
      "evYield": {},
      "battleOnly": true,
      "abilities": [],
      "moves": [],
      "evolutions": [],
      "raw": {
        "name": "Gmax",
        "primaryType": "bug",
        "secondaryType": "psychic",
        "maleRatio": 0.5,
        "height": 140,
        "weight": 0,
        "pokedex": [
          "cobblemon.species.orbeetle-gmax.desc"
        ],
        "labels": [
          "gen8",
          "gmax"
        ],
        "aspects": [
          "gmax"
        ],
        "dynamaxBlocked": true,
        "evolutions": [],
        "battleOnly": true
      }
    }
  ],
  "rawSpecies": {
    "nationalPokedexNumber": 826,
    "name": "Orbeetle",
    "primaryType": "bug",
    "secondaryType": "psychic",
    "maleRatio": 0.5,
    "height": 4,
    "weight": 408,
    "pokedex": [
      "cobblemon.species.orbeetle.desc"
    ],
    "labels": [
      "gen8"
    ],
    "aspects": [],
    "abilities": [
      "swarm",
      "frisk",
      "h:telepathy"
    ],
    "eggGroups": [
      "bug"
    ],
    "baseStats": {
      "hp": 60,
      "attack": 45,
      "defence": 110,
      "special_attack": 80,
      "special_defence": 120,
      "speed": 90
    },
    "evYield": {
      "hp": 0,
      "attack": 0,
      "defence": 0,
      "special_attack": 0,
      "special_defence": 3,
      "speed": 0
    },
    "baseExperienceYield": 253,
    "experienceGroup": "medium_fast",
    "catchRate": 45,
    "eggCycles": 15,
    "baseFriendship": 50,
    "baseScale": 1,
    "hitbox": {
      "width": 1,
      "height": 1,
      "fixed": false
    },
    "drops": {
      "amount": 2,
      "entries": [
        {
          "item": "cobblemon:psychic_seed",
          "percentage": 10
        },
        {
          "item": "cobblemon:razz_berry",
          "percentage": 10
        }
      ]
    },
    "moves": [
      "1:reflect",
      "1:lightscreen",
      "1:confusion",
      "1:strugglebug",
      "4:confuseray",
      "8:magiccoat",
      "12:agility",
      "16:psybeam",
      "20:hypnosis",
      "24:allyswitch",
      "28:bugbuzz",
      "32:mirrorcoat",
      "36:psychic",
      "40:afteryou",
      "44:calmmind",
      "48:psychicterrain",
      "egg:infestation",
      "egg:recover",
      "egg:stickyweb",
      "egg:supersonic",
      "tm:afteryou",
      "tm:agility",
      "tm:allyswitch",
      "tm:batonpass",
      "tm:bodypress",
      "tm:bugbuzz",
      "tm:calmmind",
      "tm:confuseray",
      "tm:endure",
      "tm:energyball",
      "tm:expandingforce",
      "tm:facade",
      "tm:futuresight",
      "tm:gigadrain",
      "tm:gigaimpact",
      "tm:guardswap",
      "tm:helpinghand",
      "tm:hyperbeam",
      "tm:imprison",
      "tm:infestation",
      "tm:irondefense",
      "tm:leechlife",
      "tm:lightscreen",
      "tm:magiccoat",
      "tm:magicroom",
      "tm:payback",
      "tm:powerswap",
      "tm:protect",
      "tm:psybeam",
      "tm:psychic",
      "tm:psychicterrain",
      "tm:psychocut",
      "tm:psyshock",
      "tm:reflect",
      "tm:rest",
      "tm:safeguard",
      "tm:shadowball",
      "tm:skillswap",
      "tm:sleeptalk",
      "tm:solarbeam",
      "tm:storedpower",
      "tm:strugglebug",
      "tm:substitute",
      "tm:terablast",
      "tm:trick",
      "tm:trickroom",
      "tm:uturn",
      "tm:wonderroom",
      "tm:zenheadbutt",
      "tutor:afteryou",
      "tutor:allyswitch",
      "tutor:calmmind",
      "tutor:energyball",
      "tutor:expandingforce",
      "tutor:gigadrain",
      "tutor:gigaimpact",
      "tutor:helpinghand",
      "tutor:hyperbeam",
      "tutor:irondefense",
      "tutor:leechlife",
      "tutor:magiccoat",
      "tutor:magicroom",
      "tutor:psychic",
      "tutor:psychocut",
      "tutor:rest",
      "tutor:shadowball",
      "tutor:skillswap",
      "tutor:sleeptalk",
      "tutor:trick",
      "tutor:wonderroom",
      "tutor:zenheadbutt",
      "legacy:attract",
      "legacy:round",
      "legacy:snore"
    ],
    "preEvolution": "dottler",
    "evolutions": [],
    "forms": [
      {
        "name": "Gmax",
        "primaryType": "bug",
        "secondaryType": "psychic",
        "maleRatio": 0.5,
        "height": 140,
        "weight": 0,
        "pokedex": [
          "cobblemon.species.orbeetle-gmax.desc"
        ],
        "labels": [
          "gen8",
          "gmax"
        ],
        "aspects": [
          "gmax"
        ],
        "dynamaxBlocked": true,
        "evolutions": [],
        "battleOnly": true
      }
    ],
    "behaviour": {
      "resting": {
        "willSleepOnBed": true,
        "times": [
          "day"
        ],
        "drowsyChance": 0.0033,
        "rouseChance": 0.0042
      },
      "moving": {
        "swim": {
          "avoidsWater": true
        },
        "fly": {
          "canFly": true
        },
        "walk": {
          "canWalk": false
        }
      },
      "combat": {
        "willDefendSelf": true,
        "willDefendOwner": true,
        "willFlee": false
      }
    }
  }
}
