{
  "slug": "girafarig",
  "name": "Girafarig",
  "formatId": "gen9",
  "formatLabel": "Smogon Gen 9",
  "sourceUrl": "https://pkmn.github.io/smogon/data/sets/gen9.json",
  "generatedAt": "2026-02-24T02:26:09.598Z",
  "defaultEntryName": "Girafarig",
  "defaultSets": [
    {
      "name": "Choice Specs",
      "tier": "NFE",
      "ability": "Sap Sipper",
      "item": "Choice Specs",
      "natures": [
        "Timid"
      ],
      "teraTypes": [],
      "moves": [
        [
          "Psychic"
        ],
        [
          "Hyper Voice"
        ],
        [
          "Trick"
        ],
        [
          "Nasty Plot",
          "Thunderbolt"
        ]
      ],
      "evs": {
        "spa": 252,
        "spd": 4,
        "spe": 252
      },
      "ivs": {}
    },
    {
      "name": "Nasty Plot",
      "tier": "NFE",
      "ability": "Sap Sipper",
      "item": "Eviolite",
      "natures": [
        "Timid"
      ],
      "teraTypes": [],
      "moves": [
        [
          "Nasty Plot"
        ],
        [
          "Psychic"
        ],
        [
          "Hyper Voice"
        ],
        [
          "Thunderbolt",
          "Substitute"
        ]
      ],
      "evs": {
        "spa": 252,
        "spd": 4,
        "spe": 252
      },
      "ivs": {}
    }
  ],
  "formEntries": {}
}
