{
  "slug": "spectrier",
  "name": "Spectrier",
  "formatId": "gen9",
  "formatLabel": "Smogon Gen 9",
  "sourceUrl": "https://pkmn.github.io/smogon/data/sets/gen9.json",
  "defaultEntryName": "Spectrier",
  "defaultSets": [
    {
      "name": "Audinite",
      "tier": "MIXANDMEGA",
      "ability": null,
      "item": "Audinite",
      "natures": [
        "Timid"
      ],
      "teraTypes": [],
      "moves": [
        [
          "Calm Mind",
          "Nasty Plot"
        ],
        [
          "Shadow Ball"
        ],
        [
          "Draining Kiss"
        ],
        [
          "Substitute",
          "Agility"
        ]
      ],
      "evs": {
        "hp": 128,
        "spa": 128,
        "spe": 252
      },
      "ivs": {
        "atk": 0
      }
    },
    {
      "name": "Calm Mind",
      "tier": "MONOTYPE",
      "ability": null,
      "item": "Leftovers",
      "natures": [
        "Timid"
      ],
      "teraTypes": [],
      "moves": [
        [
          "Calm Mind"
        ],
        [
          "Substitute"
        ],
        [
          "Will-O-Wisp"
        ],
        [
          "Hex"
        ]
      ],
      "evs": {
        "hp": 40,
        "def": 124,
        "spa": 144,
        "spe": 200
      },
      "ivs": {
        "atk": 0
      }
    },
    {
      "name": "Choice Specs",
      "tier": "1V1",
      "ability": null,
      "item": "Choice Specs",
      "natures": [
        "Timid"
      ],
      "teraTypes": [
        "Ghost"
      ],
      "moves": [
        [
          "Shadow Ball"
        ],
        [
          "Hyper Beam"
        ],
        [
          "Psychic"
        ],
        [
          "Mud Shot"
        ]
      ],
      "evs": {
        "hp": 80,
        "def": 32,
        "spa": 176,
        "spd": 4,
        "spe": 216
      },
      "ivs": {}
    },
    {
      "name": "Choice Specs",
      "tier": "UBERS",
      "ability": null,
      "item": "Choice Specs",
      "natures": [
        "Timid"
      ],
      "teraTypes": [
        "Fairy",
        "Fighting"
      ],
      "moves": [
        [
          "Shadow Ball"
        ],
        [
          "Tera Blast"
        ],
        [
          "Will-O-Wisp"
        ],
        [
          "Dark Pulse"
        ]
      ],
      "evs": {
        "spa": 252,
        "spd": 4,
        "spe": 252
      },
      "ivs": {
        "atk": 0
      }
    },
    {
      "name": "Life Orb",
      "tier": "1V1",
      "ability": null,
      "item": "Life Orb",
      "natures": [
        "Timid"
      ],
      "teraTypes": [],
      "moves": [
        [
          "Hex"
        ],
        [
          "Hyper Beam"
        ],
        [
          "Will-O-Wisp"
        ],
        [
          "Calm Mind"
        ]
      ],
      "evs": {
        "hp": 4,
        "def": 124,
        "spa": 180,
        "spe": 200
      },
      "ivs": {}
    },
    {
      "name": "Nasty Plot",
      "tier": "MONOTYPE",
      "ability": null,
      "item": null,
      "natures": [
        "Timid"
      ],
      "teraTypes": [],
      "moves": [
        [
          "Nasty Plot"
        ],
        [
          "Substitute",
          "Will-O-Wisp"
        ],
        [
          "Shadow Ball"
        ],
        [
          "Draining Kiss"
        ]
      ],
      "evs": {
        "spa": 252,
        "spd": 4,
        "spe": 252
      },
      "ivs": {
        "atk": 0
      }
    },
    {
      "name": "Nasty Plot",
      "tier": "UBERS",
      "ability": null,
      "item": null,
      "natures": [
        "Timid"
      ],
      "teraTypes": [
        "Fairy",
        "Fighting",
        "Ghost"
      ],
      "moves": [
        [
          "Nasty Plot"
        ],
        [
          "Substitute",
          "Taunt"
        ],
        [
          "Shadow Ball"
        ],
        [
          "Draining Kiss",
          "Tera Blast"
        ]
      ],
      "evs": {
        "spa": 252,
        "spd": 4,
        "spe": 252
      },
      "ivs": {
        "atk": 0
      }
    },
    {
      "name": "Nasty Plot",
      "tier": "DOUBLESOU",
      "ability": null,
      "item": null,
      "natures": [
        "Timid"
      ],
      "teraTypes": [
        "Fairy"
      ],
      "moves": [
        [
          "Shadow Ball"
        ],
        [
          "Draining Kiss"
        ],
        [
          "Nasty Plot"
        ],
        [
          "Protect"
        ]
      ],
      "evs": {
        "def": 136,
        "spa": 104,
        "spd": 104,
        "spe": 164
      },
      "ivs": {}
    },
    {
      "name": "Sitrus Berry + Disable",
      "tier": "1V1",
      "ability": null,
      "item": "Sitrus Berry",
      "natures": [
        "Timid"
      ],
      "teraTypes": [],
      "moves": [
        [
          "Calm Mind"
        ],
        [
          "Shadow Ball"
        ],
        [
          "Disable"
        ],
        [
          "Substitute"
        ]
      ],
      "evs": {
        "hp": 240,
        "spd": 16,
        "spe": 252
      },
      "ivs": {}
    },
    {
      "name": "Specstrier",
      "tier": "MONOTYPE",
      "ability": null,
      "item": "Choice Specs",
      "natures": [
        "Timid"
      ],
      "teraTypes": [],
      "moves": [
        [
          "Shadow Ball"
        ],
        [
          "Draining Kiss"
        ],
        [
          "Hex",
          "Psychic"
        ],
        [
          "Will-O-Wisp",
          "Psychic",
          "Hyper Beam"
        ]
      ],
      "evs": {
        "spa": 252,
        "spd": 4,
        "spe": 252
      },
      "ivs": {
        "atk": 0
      }
    }
  ],
  "formEntries": {}
}
